LICENSE.txt
README.md
setup.cfg
setup.py
BigO_TimeComplexity/__init__.py
BigO_TimeComplexity/nTimeProfiler.py
BigO_TimeComplexity.egg-info/PKG-INFO
BigO_TimeComplexity.egg-info/SOURCES.txt
BigO_TimeComplexity.egg-info/dependency_links.txt
BigO_TimeComplexity.egg-info/requires.txt
BigO_TimeComplexity.egg-info/top_level.txt